Workbook

Sheet Dashboard
A1: FUNDAMENTAL ANALYSIS — Apple Inc. (AAPL)
A2: Latest Fiscal Year: 2025-09-27
A4: GROWTH
A5: Revenue Growth | E5: EPS Growth | I5: Net Income Growth
A6: ='Income Statement'!F7 | E6: ='Income Statement'!F15 | I6: ='Income Statement'!F13
A8: PROFITABILITY
A9: Gross Margin | E9: Operating Margin | I9: Net Margin
A10: ='Income Statement'!F19 | E10: ='Income Statement'!F20 | I10: ='Income Statement'!F21
A12: FINANCIAL HEALTH
A13: Current Ratio | E13: Liabilities / Assets | I13: Equity Ratio
A14: ='Balance Sheet'!F16 | E14: ='Balance Sheet'!F17 | I14: ='Balance Sheet'!F18
A16: CASH GENERATION
A17: Operating Cash Flow | E17: Free Cash Flow | I17: FCF Margin
A18: ='Cash Flow'!F6 | E18: ='Cash Flow'!F11 | I18: ='Cash Flow'!F12
B40: FY2021 | C40: FY2022 | D40: FY2023 | E40: FY2024 | F40: FY2025

Sheet Income Statement
A1: FUNDAMENTAL ANALYSIS
A2: Apple Inc.
A3: AAPL
A5: Metric
A6: Revenue | B6: 365817000000 | C6: 394328000000 | D6: 383285000000 | E6: 391035000000 | F6: 416161000000
A7: YoY Growth | B7: N/A | C7: =IF(B6=0,"N/A",(C6-B6)/ABS(B6)) | D7: =IF(C6=0,"N/A",(D6-C6)/ABS(C6)) | E7: =IF(D6=0,"N/A",(E6-D6)/ABS(D6)) | F7: =IF(E6=0,"N/A",(F6-E6)/ABS(E6))
A8: Gross Profit | B8: 152836000000 | C8: 170782000000 | D8: 169148000000 | E8: 180683000000 | F8: 195201000000
A9: YoY Growth | B9: N/A | C9: =IF(B8=0,"N/A",(C8-B8)/ABS(B8)) | D9: =IF(C8=0,"N/A",(D8-C8)/ABS(C8)) | E9: =IF(D8=0,"N/A",(E8-D8)/ABS(D8)) | F9: =IF(E8=0,"N/A",(F8-E8)/ABS(E8))
A10: Operating Income | B10: 108949000000 | C10: 119437000000 | D10: 114301000000 | E10: 123216000000 | F10: 133050000000
A11: YoY Growth | B11: N/A | C11: =IF(B10=0,"N/A",(C10-B10)/ABS(B10)) | D11: =IF(C10=0,"N/A",(D10-C10)/ABS(C10)) | E11: =IF(D10=0,"N/A",(E10-D10)/ABS(D10)) | F11: =IF(E10=0,"N/A",(F10-E10)/ABS(E10))
A12: Net Income | B12: 94680000000 | C12: 99803000000 | D12: 96995000000 | E12: 93736000000 | F12: 112010000000
A13: YoY Growth | B13: N/A | C13: =IF(B12=0,"N/A",(C12-B12)/ABS(B12)) | D13: =IF(C12=0,"N/A",(D12-C12)/ABS(C12)) | E13: =IF(D12=0,"N/A",(E12-D12)/ABS(D12)) | F13: =IF(E12=0,"N/A",(F12-E12)/ABS(E12))
A14: Diluted EPS | B14: 5.61 | C14: 6.11 | D14: 6.13 | E14: 6.08 | F14: 7.46
A15: YoY Growth | B15: N/A | C15: =IF(B14=0,"N/A",(C14-B14)/ABS(B14)) | D15: =IF(C14=0,"N/A",(D14-C14)/ABS(C14)) | E15: =IF(D14=0,"N/A",(E14-D14)/ABS(D14)) | F15: =IF(E14=0,"N/A",(F14-E14)/ABS(E14))
A18: PROFITABILITY
A19: Gross Margin | B19: =IFERROR(B8/B6,"N/A") | C19: =IFERROR(C8/C6,"N/A") | D19: =IFERROR(D8/D6,"N/A") | E19: =IFERROR(E8/E6,"N/A") | F19: =IFERROR(F8/F6,"N/A")
A20: Operating Margin | B20: =IFERROR(B10/B6,"N/A") | C20: =IFERROR(C10/C6,"N/A") | D20: =IFERROR(D10/D6,"N/A") | E20: =IFERROR(E10/E6,"N/A") | F20: =IFERROR(F10/F6,"N/A")
A21: Net Margin | B21: =IFERROR(B12/B6,"N/A") | C21: =IFERROR(C12/C6,"N/A") | D21: =IFERROR(D12/D6,"N/A") | E21: =IFERROR(E12/E6,"N/A") | F21: =IFERROR(F12/F6,"N/A")

Sheet Balance Sheet
A1: FUNDAMENTAL ANALYSIS
A2: Apple Inc.
A3: AAPL
A5: Metric | B5: 2021-09-25 | C5: 2022-09-24 | D5: 2023-09-30 | E5: 2024-09-28 | F5: 2025-09-27
A6: Cash & Cash Equivalents | B6: 34940000000 | C6: 23646000000 | D6: 29965000000 | E6: 29943000000 | F6: 35934000000
A7: Current Assets | B7: 134836000000 | C7: 135405000000 | D7: 143566000000 | E7: 152987000000 | F7: 147957000000
A8: Current Liabilities | B8: 125481000000 | C8: 153982000000 | D8: 145308000000 | E8: 176392000000 | F8: 165631000000
A10: Total Assets | B10: 351002000000 | C10: 352755000000 | D10: 352583000000 | E10: 364980000000 | F10: 359241000000
A11: Total Liabilities | B11: 287912000000 | C11: 302083000000 | D11: 290437000000 | E11: 308030000000 | F11: 285508000000
A12: Stockholders' Equity | B12: 63090000000 | C12: 50672000000 | D12: 62146000000 | E12: 56950000000 | F12: 73733000000
A15: FINANCIAL HEALTH
A16: Current Ratio | B16: =IFERROR(B7/B8,"N/A") | C16: =IFERROR(C7/C8,"N/A") | D16: =IFERROR(D7/D8,"N/A") | E16: =IFERROR(E7/E8,"N/A") | F16: =IFERROR(F7/F8,"N/A")
A17: Liabilities / Assets | B17: =IFERROR(B11/B10,"N/A") | C17: =IFERROR(C11/C10,"N/A") | D17: =IFERROR(D11/D10,"N/A") | E17: =IFERROR(E11/E10,"N/A") | F17: =IFERROR(F11/F10,"N/A")
A18: Equity Ratio | B18: =IFERROR(B12/B10,"N/A") | C18: =IFERROR(C12/C10,"N/A") | D18: =IFERROR(D12/D10,"N/A") | E18: =IFERROR(E12/E10,"N/A") | F18: =IFERROR(F12/F10,"N/A")
A21: DATA VALIDATION
A22: Assets - (Liabilities + Equity) | B22: =B10-(B11+B12) | C22: =C10-(C11+C12) | D22: =D10-(D11+D12) | E22: =E10-(E11+E12) | F22: =F10-(F11+F12)
B40: FY2021 | C40: FY2022 | D40: FY2023 | E40: FY2024 | F40: FY2025

Sheet Cash Flow
A1: FUNDAMENTAL ANALYSIS
A2: Apple Inc.
A3: AAPL
A5: Metric | B5: 2021-09-25 | C5: 2022-09-24 | D5: 2023-09-30 | E5: 2024-09-28 | F5: 2025-09-27
A6: Operating Cash Flow | B6: 104038000000 | C6: 122151000000 | D6: 110543000000 | E6: 118254000000 | F6: 111482000000
A7: Capital Expenditures | B7: 11085000000 | C7: 10708000000 | D7: 10959000000 | E7: 9447000000 | F7: 12715000000
A10: CASH FLOW ANALYSIS
A11: Free Cash Flow | B11: =B6-B7 | C11: =C6-C7 | D11: =D6-D7 | E11: =E6-E7 | F11: =F6-F7
A12: FCF Margin | B12: =IFERROR(B11/'Income Statement'!B6,"N/A") | C12: =IFERROR(C11/'Income Statement'!C6,"N/A") | D12: =IFERROR(D11/'Income Statement'!D6,"N/A") | E12: =IFERROR(E11/'Income Statement'!E6,"N/A") | F12: =IFERROR(F11/'Income Statement'!F6,"N/A")
A13: Cash Conversion | B13: =IFERROR(B6/'Income Statement'!B12,"N/A") | C13: =IFERROR(C6/'Income Statement'!C12,"N/A") | D13: =IFERROR(D6/'Income Statement'!D12,"N/A") | E13: =IFERROR(E6/'Income Statement'!E12,"N/A") | F13: =IFERROR(F6/'Income Statement'!F12,"N/A")
